MANIFEST.in
README.txt
setup.py
src/mekk/__init__.py
src/mekk.fics.egg-info/PKG-INFO
src/mekk.fics.egg-info/SOURCES.txt
src/mekk.fics.egg-info/dependency_links.txt
src/mekk.fics.egg-info/namespace_packages.txt
src/mekk.fics.egg-info/not-zip-safe
src/mekk.fics.egg-info/requires.txt
src/mekk.fics.egg-info/top_level.txt
src/mekk/fics/__init__.py
src/mekk/fics/errors.py
src/mekk/fics/fics_client.py
src/mekk/fics/fics_client_mixin_event_methods.py
src/mekk/fics/fics_connector.py
src/mekk/fics/version.py
src/mekk/fics/command_building/__init__.py
src/mekk/fics/command_building/ivar_login.py
src/mekk/fics/constants/__init__.py
src/mekk/fics/constants/block_codes.py
src/mekk/fics/constants/limits.py
src/mekk/fics/constants/network.py
src/mekk/fics/datatypes/__init__.py
src/mekk/fics/datatypes/channel.py
src/mekk/fics/datatypes/color.py
src/mekk/fics/datatypes/date.py
src/mekk/fics/datatypes/game_clock.py
src/mekk/fics/datatypes/game_info.py
src/mekk/fics/datatypes/game_type.py
src/mekk/fics/datatypes/generic.py
src/mekk/fics/datatypes/list_items.py
src/mekk/fics/datatypes/notifications.py
src/mekk/fics/datatypes/piece.py
src/mekk/fics/datatypes/player.py
src/mekk/fics/datatypes/style12.py
src/mekk/fics/parsing/__init__.py
src/mekk/fics/parsing/common.py
src/mekk/fics/parsing/fics_parser.py
src/mekk/fics/parsing/info_parser.py
src/mekk/fics/parsing/login_parser.py
src/mekk/fics/parsing/reply_parser.py
src/mekk/fics/parsing/reply/__init__.py
src/mekk/fics/parsing/reply/block_mode_filter.py
src/mekk/fics/parsing/reply/date.py
src/mekk/fics/parsing/reply/finger.py
src/mekk/fics/parsing/reply/games.py
src/mekk/fics/parsing/reply/info.py
src/mekk/fics/parsing/reply/list_operations.py
src/mekk/fics/parsing/reply/lists.py
src/mekk/fics/parsing/reply/observe.py
src/mekk/fics/parsing/reply/play.py
src/mekk/fics/parsing/reply/seek.py
src/mekk/fics/parsing/reply/tell.py
src/mekk/fics/parsing/reply/who.py
src/mekk/fics/parsing/reply/znotify.py
src/mekk/fics/support/__init__.py
src/mekk/fics/support/block_deferreds.py
src/mekk/fics/support/delaying_executor.py
src/mekk/fics/support/keep_alive.py
src/mekk/fics/support/list_cache.py
src/mekk/fics/support/tell_status.py
src/mekk/fics/tell_commands/__init__.py
