Metadata-Version: 1.1
Name: mekk.fics
Version: 0.8.0
Summary: FICS client library.
Home-page: http://bitbucket.org/Mekk/mekk.fics/
Author: Marcin Kasperski
Author-email: Marcin.Kasperski@mekk.waw.pl
License: Artistic
Keywords: FICS,chess
Platform: UNKNOWN
Classifier: Programming Language :: Python :: 2
Classifier: Programming Language :: Python :: 3
Classifier: Intended Audience :: Developers
Classifier: Topic :: Software Development :: Libraries :: Python Modules
Classifier: License :: OSI Approved :: Mozilla Public License 1.1 (MPL 1.1)
Classifier: License :: OSI Approved :: Artistic License
Classifier: Development Status :: 4 - Beta
Classifier: Intended Audience :: Developers
Classifier: Operating System :: OS Independent
